odoo8_addon_base_debug4all-8.0.1.0.0-py2.7-nspkg.pth
odoo8_addon_base_debug4all-8.0.1.0.0.dist-info/top_level.txt
odoo8_addon_base_debug4all-8.0.1.0.0.dist-info/WHEEL
odoo8_addon_base_debug4all-8.0.1.0.0.dist-info/RECORD
odoo8_addon_base_debug4all-8.0.1.0.0.dist-info/metadata.json
odoo8_addon_base_debug4all-8.0.1.0.0.dist-info/DESCRIPTION.rst
odoo8_addon_base_debug4all-8.0.1.0.0.dist-info/METADATA
odoo8_addon_base_debug4all-8.0.1.0.0.dist-info/namespace_packages.txt
odoo_addons/base_debug4all/__openerp__.py
odoo_addons/base_debug4all/__init__.py
odoo_addons/base_debug4all/README.rst
odoo_addons/base_debug4all/static/description/icon.png
odoo_addons/base_debug4all/static/src/xml/base.xml
