Metadata-Version: 2.0
Name: odoo8-addon-base-debug4all
Version: 8.0.1.0.0
Summary: Shows full debug options for all users
Home-page: UNKNOWN
Author: UNKNOWN
Author-email: UNKNOWN
License: AGPL-3
Platform: UNKNOWN
Requires-Dist: odoo (<9.0a,>=8.0a)
Classifier: Programming Language :: Python :: 2.7
Classifier: Framework :: Odoo
Classifier: License :: OSI Approved :: GNU Affero General Public License v3
